td/__init__.py
td/certs.py
td/client.py
td/enums.py
td/exceptions.py
td/message.py
td/oauth.py
td/option_chain.py
td/orders.py
td/stream.py
td/utils.py
td/watchlist_item.py
td/app/auth.py
td/templates/auth.html
td/templates/index.html
td_ameritrade_python_api-0.3.5.dist-info/LICENSE
td_ameritrade_python_api-0.3.5.dist-info/METADATA
td_ameritrade_python_api-0.3.5.dist-info/WHEEL
td_ameritrade_python_api-0.3.5.dist-info/top_level.txt
td_ameritrade_python_api-0.3.5.dist-info/RECORD
