Metadata-Version: 2.1
Name: td-ameritrade-python-api
Version: 0.3.5
Summary: A python client lirbary for the TD Ameritrade API.
Home-page: https://github.com/areed1192/td-ameritrade-python-api
Author: Alex Reed
Author-email: coding.sigma@gmail.com
License: UNKNOWN
Keywords: finance,td ameritrade,api
Platform: UNKNOWN
Classifier: Development Status :: 3 - Alpha
Classifier: Intended Audience :: Financial and Insurance Industry
Classifier: License :: OSI Approved :: MIT License
Classifier: Natural Language :: English
Classifier: Operating System :: OS Independent
Classifier: Programming Language :: Python :: 3
Requires-Python: >=3.7
